cmd_line_mcp/__init__.py
cmd_line_mcp/config.py
cmd_line_mcp/security.py
cmd_line_mcp/server.py
cmd_line_mcp/session.py
cmd_line_mcp-0.5.0.data/data/default_config.json
cmd_line_mcp-0.5.0.dist-info/licenses/LICENSE
cmd_line_mcp-0.5.0.dist-info/METADATA
cmd_line_mcp-0.5.0.dist-info/WHEEL
cmd_line_mcp-0.5.0.dist-info/entry_points.txt
cmd_line_mcp-0.5.0.dist-info/top_level.txt
cmd_line_mcp-0.5.0.dist-info/RECORD
